{
  "id" : "VXPAKOKS240784820",
  "opertor" : "label20",
  "krlgg_sntenc" : {
    "koreanText" : "모든 행복 중에 먹는 행복이 최고인 거 같아.",
    "category" : "수어 > 무작위 구성",
    "realm" : "일상생활",
    "thema" : "일상생활 말뭉치",
    "detailThema" : "일상생활 말뭉치"
  },
  "sign_script" : {
    "sign_gestures_strong" : [ {
      "start" : 2.926,
      "end" : 3.267,
      "gloss_id" : "행복1",
      "express" : "s",
      "direction" : {
        "source" : "",
        "target" : ""
      }
    }, {
      "start" : 3.475,
      "end" : 3.975,
      "gloss_id" : "지시1#",
      "express" : "s",
      "direction" : {
        "source" : "",
        "target" : ""
      }
    }, {
      "start" : 4.232,
      "end" : 4.645,
      "gloss_id" : "등수:1등",
      "express" : "d",
      "direction" : {
        "source" : "",
        "target" : ""
      }
    }, {
      "start" : 4.882,
      "end" : 5.115,
      "gloss_id" : "행복1",
      "express" : "s",
      "direction" : {
        "source" : "",
        "target" : ""
      }
    }, {
      "start" : 5.265,
      "end" : 5.397,
      "gloss_id" : "무엇1",
      "express" : "s",
      "direction" : {
        "source" : "",
        "target" : ""
      }
    }, {
      "start" : 5.655,
      "end" : 6.234,
      "gloss_id" : "먹다1",
      "express" : "s",
      "direction" : {
        "source" : "",
        "target" : ""
      }
    } ],
    "sentence_loc" : [ {
      "start" : 2.926,
      "end" : 3.267,
      "loc" : "1",
      "word" : "행복"
    }, {
      "start" : 3.475,
      "end" : 3.975,
      "loc" : "0,2",
      "word" : "모든 중에"
    }, {
      "start" : 5.655,
      "end" : 6.234,
      "loc" : "3",
      "word" : "먹는"
    }, {
      "start" : 4.232,
      "end" : 5.389,
      "loc" : "4,5,6,7",
      "word" : "행복이 최고인 거 같아."
    } ],
    "sign_gestures_weak" : null
  },
  "nms_script" : {
    "Mmo" : null,
    "Hno" : [ {
      "descriptor" : "",
      "start" : 5.655,
      "end" : 6.234
    } ],
    "Mo1" : null,
    "Hs" : null,
    "EBf" : null,
    "Mctr" : null,
    "Ci" : null,
    "Ebu" : null
  },
  "vido_file_nm" : "VXPAKOKS240784820",
  "potogrf" : {
    "createdTime" : "2024-08-21 11:24:43",
    "sentence_ID" : "VXPAKOKS240784820",
    "photographer" : "D",
    "location" : "d",
    "devide" : "Sony A6400",
    "iris" : 4.0,
    "gain" : "ISO 400",
    "whiteBalance" : 6000,
    "shutterSpeed" : "1/125",
    "fps" : 30.0,
    "width" : 1920,
    "height" : 1080,
    "format" : "MP4",
    "codec" : "XAVC S HD",
    "sl_speaker_id" : "EJ",
    "sl_speaker_age" : 40,
    "sl_speaker_sex" : "female",
    "sl_speaker_legion" : "Seoul",
    "sl_speaker_hand" : "right_handed"
  },
  "license" : "국립국어원"
}