{
  "id" : "VXPAKOKS240783080",
  "opertor" : "label20",
  "krlgg_sntenc" : {
    "koreanText" : "너는 만약에 다이어트해서 너가 원하는 몸을 갖게 된다면 뭘 제일 하고 싶어?",
    "category" : "수어 > 무작위 구성",
    "realm" : "일상생활",
    "thema" : "일상생활 말뭉치",
    "detailThema" : "일상생활 말뭉치"
  },
  "sign_script" : {
    "sign_gestures_strong" : [ {
      "start" : 1.563,
      "end" : 1.725,
      "gloss_id" : "지시1#",
      "express" : "s",
      "direction" : {
        "source" : "",
        "target" : ""
      }
    }, {
      "start" : 1.919,
      "end" : 2.253,
      "gloss_id" : "만약2",
      "express" : "s",
      "direction" : {
        "source" : "",
        "target" : ""
      }
    }, {
      "start" : 2.527,
      "end" : 2.732,
      "gloss_id" : "고기1",
      "express" : "s",
      "direction" : {
        "source" : "",
        "target" : ""
      }
    }, {
      "start" : 3.012,
      "end" : 3.534,
      "gloss_id" : "좁다1",
      "express" : "s",
      "direction" : {
        "source" : "",
        "target" : ""
      }
    }, {
      "start" : 3.746,
      "end" : 3.872,
      "gloss_id" : "지시1#",
      "express" : "s",
      "direction" : {
        "source" : "",
        "target" : ""
      }
    }, {
      "start" : 4.175,
      "end" : 4.754,
      "gloss_id" : "원하다1",
      "express" : "s",
      "direction" : {
        "source" : "",
        "target" : ""
      }
    }, {
      "start" : 4.945,
      "end" : 5.373,
      "gloss_id" : "몸1",
      "express" : "s",
      "direction" : {
        "source" : "",
        "target" : ""
      }
    }, {
      "start" : 5.657,
      "end" : 5.92,
      "gloss_id" : "같다1",
      "express" : "s",
      "direction" : {
        "source" : "",
        "target" : ""
      }
    }, {
      "start" : 6.131,
      "end" : 6.257,
      "gloss_id" : "등수:1등",
      "express" : "d",
      "direction" : {
        "source" : "",
        "target" : ""
      }
    }, {
      "start" : 6.331,
      "end" : 6.551,
      "gloss_id" : "번째:1번째",
      "express" : "d",
      "direction" : {
        "source" : "",
        "target" : ""
      }
    }, {
      "start" : 6.72,
      "end" : 6.824,
      "gloss_id" : "원하다1",
      "express" : "s",
      "direction" : {
        "source" : "",
        "target" : ""
      }
    }, {
      "start" : 6.929,
      "end" : 7.141,
      "gloss_id" : "무엇1",
      "express" : "s",
      "direction" : {
        "source" : "",
        "target" : ""
      }
    } ],
    "sentence_loc" : [ {
      "start" : 1.563,
      "end" : 1.725,
      "loc" : "0",
      "word" : "너는"
    }, {
      "start" : 1.919,
      "end" : 2.253,
      "loc" : "1",
      "word" : "만약에"
    }, {
      "start" : 2.527,
      "end" : 3.53,
      "loc" : "2",
      "word" : "다이어트해서"
    }, {
      "start" : 3.746,
      "end" : 3.872,
      "loc" : "3",
      "word" : "너가"
    }, {
      "start" : 4.175,
      "end" : 4.754,
      "loc" : "4",
      "word" : "원하는"
    }, {
      "start" : 4.945,
      "end" : 5.373,
      "loc" : "5",
      "word" : "몸을"
    }, {
      "start" : 5.657,
      "end" : 5.92,
      "loc" : "6,7",
      "word" : "갖게 된다면"
    }, {
      "start" : 6.131,
      "end" : 6.552,
      "loc" : "9",
      "word" : "제일"
    }, {
      "start" : 6.72,
      "end" : 6.824,
      "loc" : "10,11",
      "word" : "하고 싶어?"
    }, {
      "start" : 6.929,
      "end" : 7.141,
      "loc" : "8",
      "word" : "뭘"
    } ],
    "sign_gestures_weak" : [ {
      "start" : 1.919,
      "end" : 2.253,
      "gloss_id" : "만약2",
      "express" : "s",
      "direction" : null,
      "sentence_loc" : null
    }, {
      "start" : 2.527,
      "end" : 2.732,
      "gloss_id" : "고기1",
      "express" : "s",
      "direction" : null,
      "sentence_loc" : null
    }, {
      "start" : 3.012,
      "end" : 3.534,
      "gloss_id" : "좁다1",
      "express" : "s",
      "direction" : null,
      "sentence_loc" : null
    }, {
      "start" : 4.945,
      "end" : 5.373,
      "gloss_id" : "몸1",
      "express" : "s",
      "direction" : null,
      "sentence_loc" : null
    }, {
      "start" : 5.657,
      "end" : 5.92,
      "gloss_id" : "같다1",
      "express" : "s",
      "direction" : null,
      "sentence_loc" : null
    }, {
      "start" : 6.331,
      "end" : 6.551,
      "gloss_id" : "번째:1번째",
      "express" : "d",
      "direction" : null,
      "sentence_loc" : null
    } ]
  },
  "nms_script" : {
    "Mmo" : null,
    "Hno" : [ {
      "descriptor" : "",
      "start" : 1.919,
      "end" : 2.253
    }, {
      "descriptor" : "",
      "start" : 3.012,
      "end" : 3.534
    }, {
      "descriptor" : "",
      "start" : 5.657,
      "end" : 5.928
    }, {
      "descriptor" : "",
      "start" : 6.929,
      "end" : 7.141
    } ],
    "Mo1" : [ {
      "descriptor" : "",
      "start" : 5.822,
      "end" : 5.92
    } ],
    "Hs" : null,
    "EBf" : [ {
      "descriptor" : "",
      "start" : 1.919,
      "end" : 2.253
    } ],
    "Mctr" : [ {
      "descriptor" : "",
      "start" : 1.563,
      "end" : 2.255
    }, {
      "descriptor" : "",
      "start" : 3.012,
      "end" : 3.435
    }, {
      "descriptor" : "",
      "start" : 6.131,
      "end" : 6.53
    } ],
    "Ci" : null,
    "Ebu" : [ {
      "descriptor" : "",
      "start" : 2.527,
      "end" : 2.732
    }, {
      "descriptor" : "",
      "start" : 5.657,
      "end" : 5.92
    }, {
      "descriptor" : "",
      "start" : 6.929,
      "end" : 7.141
    } ]
  },
  "vido_file_nm" : "VXPAKOKS240783080",
  "potogrf" : {
    "createdTime" : "2024-08-21 11:15:45",
    "sentence_ID" : "VXPAKOKS240783080",
    "photographer" : "D",
    "location" : "d",
    "devide" : "Sony A6400",
    "iris" : 4.0,
    "gain" : "ISO 400",
    "whiteBalance" : 6000,
    "shutterSpeed" : "1/125",
    "fps" : 30.0,
    "width" : 1920,
    "height" : 1080,
    "format" : "MP4",
    "codec" : "XAVC S HD",
    "sl_speaker_id" : "EJ",
    "sl_speaker_age" : 40,
    "sl_speaker_sex" : "female",
    "sl_speaker_legion" : "Seoul",
    "sl_speaker_hand" : "right_handed"
  },
  "license" : "국립국어원"
}